anonip.py
anonip-1.1.0.dist-info/LICENSE.txt
anonip-1.1.0.dist-info/METADATA
anonip-1.1.0.dist-info/WHEEL
anonip-1.1.0.dist-info/entry_points.txt
anonip-1.1.0.dist-info/top_level.txt
anonip-1.1.0.dist-info/RECORD
