Metadata-Version: 2.1
Name: anonip
Version: 1.1.0
Summary: Anonip is a tool to anonymize IP-addresses in log-files.
Home-page: https://github.com/DigitaleGesellschaft/Anonip
Author: Digitale Gesellschaft
License: BSD
Platform: UNKNOWN
Classifier: Development Status :: 4 - Beta
Classifier: Intended Audience :: System Administrators
Classifier: License :: OSI Approved :: BSD License
Classifier: Programming Language :: Python :: 2.7
Classifier: Programming Language :: Python :: 3
Classifier: Programming Language :: Python :: Implementation :: PyPy
License-File: LICENSE.txt
Requires-Dist: ipaddress ; python_version < "3.3"
